LICENSE
MANIFEST.in
README
TODO.txt
build_docs.sh
setup.py
docs/Makefile
docs/getting_started.rst
docs/index.rst
docs/signals.rst
docs/_static/breadcrumb_background.png
docs/_static/default.css
docs/_static/documentation.png
docs/_static/header_sm_mid.png
docs/_static/scrn1.png
docs/_static/scrn2.png
docs/_static/searchfield_leftcap.png
docs/_static/searchfield_repeat.png
docs/_static/searchfield_rightcap.png
docs/_static/title_background.png
docs/_static/toc.js
docs/_static/triangle_closed.png
docs/_static/triangle_left.png
docs/_static/triangle_open.png
docs/_templates/layout.html
docs/reference/index.rst
docs/reference/permmgrref.rst
docs/reference/usergroupref.rst
example/__init__.py
example/manage.py
example/settings.py
example/urls.py
example/fixtures/simpleapp.json
example/simpleapp/__init__.py
example/simpleapp/models.py
example/simpleapp/tests.py
example/simpleapp/views.py
objectpermissions/__init__.py
objectpermissions/admin.py
objectpermissions/decorators.py
objectpermissions/models.py
objectpermissions/registration.py
objectpermissions/signals.py
objectpermissions/tests.py
objectpermissions/views.py
objectpermissions.egg-info/PKG-INFO
objectpermissions.egg-info/SOURCES.txt
objectpermissions.egg-info/dependency_links.txt
objectpermissions.egg-info/top_level.txt